convexpanou/__init__.py
convexpanou/conv.py
convexpanou/conv2.py
convexpanou-0.1.0.dist-info/LICENSE
convexpanou-0.1.0.dist-info/METADATA
convexpanou-0.1.0.dist-info/WHEEL
convexpanou-0.1.0.dist-info/top_level.txt
convexpanou-0.1.0.dist-info/RECORD
