Metadata-Version: 2.1
Name: convexpanou
Version: 0.1.0
Summary: Creates convex hulls of 2-d arrays
Home-page: https://github.com/nhvd3500/PANOU
Author: Kostas Panoutsakos
Author-email: panou10_@hotmail.com
License: MIT
Platform: UNKNOWN
Requires-Dist: numpy
Requires-Dist: matplotlib
